{
  "type": "minecraft:block",
  "pools": [
    {
      "bonus_rolls": 0.0,
      "entries": [
        {
          "type": "minecraft:alternatives",
          "children": [
            {
              "type": "minecraft:item",
              "conditions": [
                {
                  "condition": "minecraft:match_tool",
                  "predicate": {
                    "enchantments": [
                      {
                        "enchantment": "minecraft:silk_touch",
                        "levels": {
                          "min": 1
                        }
                      }
                    ]
                  }
                }
              ],
              "name": "ae2:mysterious_cube"
            },
            {
              "type": "minecraft:tag",
              "conditions": [
                {
                  "condition": "minecraft:survives_explosion"
                }
              ],
              "expand": false,
              "name": "ae2:inscriber_presses"
            }
          ]
        }
      ],
      "rolls": 1.0
    }
  ]
}