{
  "required": true,
  "minVersion": "0.8.3",
  "package": "appeng.mixins",
  "refmap": "appliedenergistics2.mixins.refmap.json",
  "compatibilityLevel": "JAVA_11",
  "mixins": [
    "spatial.DimensionTypeMixin",
    "spatial.DimensionOptionMixin",
    "structure.DimensionStructuresSettingsMixin",
    "structure.ConfiguredStructureFeaturesAccessor",
    "feature.ConfiguredFeaturesAccessor",
    "feature.LevelLightEngineMixin",
    "EarlyStartupMixin"
  ],
  "client": [
    "spatial.SkyRenderMixin",
    "spatial.SkyPropertiesMixin",
    "unlitquad.ModelBakeryMixin",
    "unlitquad.BlockModelMixin",
    "unlitquad.BlockPartFaceDeserializerMixin",
    "unlitquad.BakedQuadAccessor",
    "RenderEncodedPatternMixin"
  ],
  "server": [],
  "injectors": {
    "defaultRequire": 1
  }
}
