{
    "result": {
        "item": "appliedenergistics2:drive"
    },
    "type": "forge:ore_shaped",
    "pattern": [
        "aba",
        "c c",
        "aba"
    ],
    "key": {
        "b": {
            "type": "appliedenergistics2:part",
            "part": "material.engineering_processor"
        },
        "a": {
            "type": "forge:ore_dict",
            "ore": "ingotIron"
        },
        "c": {
            "type": "appliedenergistics2:part",
            "part": "cable_glass.fluix"
        }
    }
}
