{
    "conditions": [
        {
            "type": "forge:and",
            "values": [
                {
                    "type": "minecraft:item_exists",
                    "item": "appliedenergistics2:quartz_glass"
                },
                {
                    "type": "appliedenergistics2:material_exists",
                    "material": "material.fluid_cell64k_part"
                },
                {
                    "type": "appliedenergistics2:material_exists",
                    "material": "material.fluid_cell16k_part"
                },
                {
                    "type": "appliedenergistics2:material_exists",
                    "material": "material.calculation_processor"
                }
            ]
        }
    ],
    "result": {
        "type": "appliedenergistics2:part",
        "part": "material.fluid_cell64k_part"
    },
    "type": "appliedenergistics2:part_shaped",
    "pattern": [
        "aba",
        "cdc",
        "aca"
    ],
    "key": {
        "d": {
            "item": "appliedenergistics2:quartz_glass"
        },
        "a": {
            "item": "minecraft:dye",
            "data": 4
        },
        "c": {
            "type": "appliedenergistics2:part",
            "part": "material.fluid_cell16k_part"
        },
        "b": {
            "type": "appliedenergistics2:part",
            "part": "material.calculation_processor"
        }
    }
}
